geenext/__init__.py
geenext/common.py
geenext/extraction.py
geenext/geenext.py
geenext-1.0.1.dist-info/LICENSE
geenext-1.0.1.dist-info/METADATA
geenext-1.0.1.dist-info/WHEEL
geenext-1.0.1.dist-info/entry_points.txt
geenext-1.0.1.dist-info/top_level.txt
geenext-1.0.1.dist-info/RECORD
