Metadata-Version: 2.1
Name: geenext
Version: 1.0.1
Summary: A python package to extend the capabilities of Google Earth Engine in the field of Al and ML.
Author-email: Krish Halder <geonextgis@gmail.com>
License: MIT License
Project-URL: Homepage, https://github.com/geonextgis/geenext
Keywords: geenext
Classifier: Intended Audience :: Developers
Classifier: License :: OSI Approved :: MIT License
Classifier: Natural Language :: English
Classifier: Programming Language :: Python :: 3.8
Classifier: Programming Language :: Python :: 3.9
Classifier: Programming Language :: Python :: 3.10
Classifier: Programming Language :: Python :: 3.11
Classifier: Programming Language :: Python :: 3.12
Requires-Python: >=3.8
License-File: LICENSE
Requires-Dist: numpy
Requires-Dist: pandas
Requires-Dist: ee
Requires-Dist: geemap
Requires-Dist: geopandas
Requires-Dist: tqdm
Provides-Extra: all
Requires-Dist: geenext[extra] ; extra == 'all'
Provides-Extra: extra
Requires-Dist: pandas ; extra == 'extra'
